pytoxr/__init__.py
pytoxr/collect.py
pytoxr/mathfunctions.py
pytoxr/parse.py
pytoxr/plot.py
pytoxr/toolkit.py
pytoxr/fit_to_sine/__init__.py
pytoxr/fit_to_sine/fit_to_sine.py
pytoxr/scanmut/__init__.py
pytoxr/scanmut/scanmut.py
pytoxr-0.0.7.dist-info/METADATA
pytoxr-0.0.7.dist-info/RECORD
pytoxr-0.0.7.dist-info/WHEEL
pytoxr-0.0.7.dist-info/top_level.txt
