Metadata-Version: 2.1
Name: pytoxr
Version: 0.0.7
Summary: Tools for the analysis of data from ToxR experiments.
Home-page: https://github.com/teese/pytoxr
Author: Mark Teese
Author-email: mark.teese@checkmytumhomepage.de
License: MIT
Download-URL: https://github.com/teese/pytoxr/archive/0.0.7.tar.gz
Project-URL: LangoschLab, http://cbp.wzw.tum.de/index.php?id=9
Project-URL: TU_Munich, https://www.tum.de
Keywords: ToxR transmembrane TOXCAT TMDhomodimer GALLEX AraTM BacTH
Platform: UNKNOWN
Classifier: Intended Audience :: Science/Research
Classifier: License :: OSI Approved :: MIT License
Classifier: Programming Language :: Python :: 3
Classifier: Topic :: Scientific/Engineering :: Bio-Informatics
Classifier: Topic :: Scientific/Engineering :: Chemistry
Requires-Dist: pandas
Requires-Dist: numpy
Requires-Dist: matplotlib
Requires-Dist: scipy
Requires-Dist: seaborn
Requires-Dist: eccpy
